hudu_py/API.py
hudu_py/___init__.py
hudu_py-0.0.2.dist-info/LICENSE
hudu_py-0.0.2.dist-info/METADATA
hudu_py-0.0.2.dist-info/WHEEL
hudu_py-0.0.2.dist-info/top_level.txt
hudu_py-0.0.2.dist-info/RECORD
